liquidtap/__init__.py
liquidtap/client.py
liquidtap/utils.py
liquidtap/pysher/__init__.py
liquidtap/pysher/channel.py
liquidtap/pysher/connection.py
liquidtap/pysher/pusher.py
liquidtap-1.0.3.dist-info/LICENSE
liquidtap-1.0.3.dist-info/METADATA
liquidtap-1.0.3.dist-info/WHEEL
liquidtap-1.0.3.dist-info/top_level.txt
liquidtap-1.0.3.dist-info/RECORD
