Metadata-Version: 2.1
Name: liquidtap
Version: 1.0.3
Summary: QuoineFinancial/LiquidTap websocket client for Python
Home-page: https://github.com/QuoineFinancial/liquid-tap-python
Author: Jered Masters
Author-email: jered.masters@quoine.com
License: MIT
Keywords: pusher websocket client liquid liquidapi liquidtap
Classifier: Programming Language :: Python :: 3
Classifier: License :: OSI Approved :: MIT License
Classifier: Operating System :: OS Independent
License-File: LICENSE
Requires-Dist: websocket-client (!=0.49)
